digid_eherkenning/__init__.py
digid_eherkenning/_xml.py
digid_eherkenning/admin.py
digid_eherkenning/apps.py
digid_eherkenning/backends.py
digid_eherkenning/choices.py
digid_eherkenning/digid_urls.py
digid_eherkenning/eherkenning_urls.py
digid_eherkenning/exceptions.py
digid_eherkenning/forms.py
digid_eherkenning/managers.py
digid_eherkenning/metadata_urls.py
digid_eherkenning/mock_urls.py
digid_eherkenning/py.typed
digid_eherkenning/settings.py
digid_eherkenning/types.py
digid_eherkenning/urls.py
digid_eherkenning/utils.py
digid_eherkenning/validators.py
digid_eherkenning/locale/nl/LC_MESSAGES/django.mo
digid_eherkenning/locale/nl/LC_MESSAGES/django.po
digid_eherkenning/management/__init__.py
digid_eherkenning/management/utils.py
digid_eherkenning/management/commands/__init__.py
digid_eherkenning/management/commands/update_stored_metadata.py
digid_eherkenning/migrations/0001_initial.py
digid_eherkenning/migrations/0001_initial_to_v019.py
digid_eherkenning/migrations/0002_auto_20221102_1046.py
digid_eherkenning/migrations/0002_mockdigiduser.py
digid_eherkenning/migrations/0003_alter_mockdigiduser_options.py
digid_eherkenning/migrations/0003_digidconfiguration_artifact_resolve_content_type.py
digid_eherkenning/migrations/0004_alter_eherkenningconfiguration_loa.py
digid_eherkenning/migrations/0004_alter_mockdigiduser_bsn.py
digid_eherkenning/migrations/0005_alter_eherkenningconfiguration_eh_service_instance_uuid_and_more.py
digid_eherkenning/migrations/0005_configcertificate_activation_date.py
digid_eherkenning/migrations/0006_digidconfiguration_metadata_file_source_and_more.py
digid_eherkenning/migrations/0007_eherkenningconfiguration_service_description_url.py
digid_eherkenning/migrations/0008_update_loa_fields.py
digid_eherkenning/migrations/0009_decrypt_private_keys.py
digid_eherkenning/migrations/0010_remove_digidconfiguration_key_passphrase_and_more.py
digid_eherkenning/migrations/0011_configcertificate_configcertificate_uniq_config_cert.py
django_digid_eherkenning-0.24.0.dist-info/licenses/LICENSE
django_digid_eherkenning-0.24.0.dist-info/METADATA
django_digid_eherkenning-0.24.0.dist-info/WHEEL
django_digid_eherkenning-0.24.0.dist-info/top_level.txt
django_digid_eherkenning-0.24.0.dist-info/RECORD
