Metadata-Version: 2.4
Name: django-digid-eherkenning
Version: 0.24.0
Summary: A Django app for DigiD/eHerkenning authentication flows
Author-email: Maykin Media <support@maykinmedia.nl>
License-Expression: MIT
Project-URL: Homepage, https://github.com/maykinmedia/django-digid-eherkenning
Project-URL: Documentation, https://django-digid-eherkenning.readthedocs.io/en/latest/
Project-URL: Bug Tracker, https://github.com/maykinmedia/django-digid-eherkenning/issues
Project-URL: Source Code, https://github.com/maykinmedia/django-digid-eherkenning
Project-URL: Changelog, https://github.com/maykinmedia/django-digid-eherkenning/blob/master/CHANGELOG.rst
Keywords: django,authentication,digid,eherkenning,eidas,dutch,nl,netherlands
Classifier: Development Status :: 4 - Beta
Classifier: Framework :: Django
Classifier: Framework :: Django :: 4.2
Classifier: Framework :: Django :: 5.2
Classifier: Intended Audience :: Developers
Classifier: Operating System :: Unix
Classifier: Operating System :: MacOS
Classifier: Operating System :: Microsoft :: Windows
Classifier: Programming Language :: Python :: 3.10
Classifier: Programming Language :: Python :: 3.11
Classifier: Programming Language :: Python :: 3.12
Classifier: Programming Language :: Python :: 3.13
Classifier: Topic :: Software Development :: Libraries :: Python Modules
Requires-Python: >=3.10
License-File: LICENSE
Requires-Dist: cryptography>=40.0.0
Requires-Dist: django>=4.2.0
Requires-Dist: django-sessionprofile
Requires-Dist: django-simple-certmanager>=2.3.0
Requires-Dist: django-solo
Requires-Dist: lxml>=4.7.1
Requires-Dist: furl
Requires-Dist: maykin-python3-saml>=1.16.0
Provides-Extra: oidc
Requires-Dist: mozilla-django-oidc-db>=0.24.0; extra == "oidc"
Provides-Extra: tests
Requires-Dist: django-test-migrations; extra == "tests"
Requires-Dist: pytest; extra == "tests"
Requires-Dist: pytest-cov; extra == "tests"
Requires-Dist: pytest-django; extra == "tests"
Requires-Dist: pytest-mock; extra == "tests"
Requires-Dist: responses; extra == "tests"
Requires-Dist: freezegun; extra == "tests"
Requires-Dist: tox; extra == "tests"
Requires-Dist: ruff; extra == "tests"
Provides-Extra: docs
Requires-Dist: sphinx; extra == "docs"
Requires-Dist: sphinx-rtd-theme; extra == "docs"
Requires-Dist: psycopg; extra == "docs"
Provides-Extra: release
Requires-Dist: bump-my-version; extra == "release"
Requires-Dist: build; extra == "release"
Dynamic: license-file
